{
  "items": [
    {
      "sys": { "id": "1" },
      "fields": {
        "title": "Adidas Dame 6",
        "price": 10.99,
        "image": { "fields": { "file": { "url": "../images/adidas-Dame-6.jpg" } } }
      }
    },
    {
      "sys": { "id": "2" },
      "fields": {
        "title": "Adidas D-Rose 8",
        "price": 12.99,
        "image": { "fields": { "file": { "url": "../images/Adidas-D-Rose-8.png" } } }
      }
    },
    {
      "sys": { "id": "3" },
      "fields": {
        "title": "Air Jordan 6",
        "price": 12.99,
        "image": { "fields": { "file": { "url": "../images/air-jordan-xi.jpg" } } }
      }
    },
    {
      "sys": { "id": "4" },
      "fields": {
        "title": "Anta Rajon Rondo RR5",
        "price": 12.99,
        "image": { "fields": { "file": { "url": "../images/ANTA-Rajon-Rondo-RR5.jpg" } } }
      }
    },
    {
      "sys": { "id": "5" },
      "fields": {
        "title": "Nike Kobe 12",
        "price": 12.99,
        "image": { "fields": { "file": { "url": "../images/img01.jpg" } } }
      }
    },
    {
      "sys": { "id": "6" },
      "fields": {
        "title": "Nike KD 12",
        "price": 12.99,
        "image": { "fields": { "file": { "url": "../images/Nike-KD12.jpg" } } }
      }
    },
    {
      "sys": { "id": "7" },
      "fields": {
        "title": "Nike Kyrie 6",
        "price": 12.99,
        "image": { "fields": { "file": { "url": "../images/Nike-Kyrie-6.png" } } }
      }
    },
    {
      "sys": { "id": "8" },
      "fields": {
        "title": "Under Armour Curry 6",
        "price": 12.99,
        "image": { "fields": { "file": { "url": "../images/Under-Armour-Curry-6.jpg" } } }
      }
    }
  ]
}
